CHANGES.rst
CONTRIBUTORS.rst
MANIFEST.in
README.rst
setup.cfg
setup.py
docs/LICENSE.GPL
docs/LICENSE.txt
src/collective/__init__.py
src/collective/__init__.pyc
src/collective.behavior.localregistry.egg-info/PKG-INFO
src/collective.behavior.localregistry.egg-info/SOURCES.txt
src/collective.behavior.localregistry.egg-info/dependency_links.txt
src/collective.behavior.localregistry.egg-info/entry_points.txt
src/collective.behavior.localregistry.egg-info/namespace_packages.txt
src/collective.behavior.localregistry.egg-info/not-zip-safe
src/collective.behavior.localregistry.egg-info/requires.txt
src/collective.behavior.localregistry.egg-info/top_level.txt
src/collective/behavior/__init__.py
src/collective/behavior/__init__.pyc
src/collective/behavior/localregistry/__init__.py
src/collective/behavior/localregistry/__init__.pyc
src/collective/behavior/localregistry/behavior.py
src/collective/behavior/localregistry/behavior.pyc
src/collective/behavior/localregistry/configure.zcml
src/collective/behavior/localregistry/events.py
src/collective/behavior/localregistry/events.pyc
src/collective/behavior/localregistry/interfaces.py
src/collective/behavior/localregistry/interfaces.pyc
src/collective/behavior/localregistry/proxy.py
src/collective/behavior/localregistry/proxy.pyc
src/collective/behavior/localregistry/proxy.rst
src/collective/behavior/localregistry/subscribers.py
src/collective/behavior/localregistry/subscribers.pyc
src/collective/behavior/localregistry/testing.py
src/collective/behavior/localregistry/testing.pyc
src/collective/behavior/localregistry/tests/__init__.py
src/collective/behavior/localregistry/tests/__init__.pyc
src/collective/behavior/localregistry/tests/test_setup.py
src/collective/behavior/localregistry/tests/test_setup.pyc