Metadata-Version: 1.1
Name: collective.behavior.localregistry
Version: 1.0b2
Summary: Dexterity behavior to add a local plone.app.registry for           content types, it adds a local component with a layered           proxy registry.
Home-page: https://github.com/collective/collective.behavior.localregistry
Author: Simples Consultoria
Author-email: products@simplesconsultoria.com.br
License: UNKNOWN
Keywords: plone registry local behavior dexterity
Platform: UNKNOWN
Classifier: Development Status :: 4 - Beta
Classifier: Environment :: Web Environment
Classifier: Framework :: Plone
Classifier: Framework :: Plone :: 4.1
Classifier: Framework :: Plone :: 4.2
Classifier: Framework :: Plone :: 4.3
Classifier: Intended Audience :: End Users/Desktop
Classifier: Intended Audience :: System Administrators
Classifier: License :: OSI Approved :: GNU General Public License v2 (GPLv2)
Classifier: Operating System :: OS Independent
Classifier: Programming Language :: Python
Classifier: Programming Language :: Python :: 2.6
Classifier: Programming Language :: Python :: 2.7
Classifier: Topic :: Software Development :: Libraries :: Python Modules
